Workbook
Name aporte: APP!$D$22
Name patrimonio: APP!$D$25
Name qtd_anos: APP!$D$23
Name rendimento_carteira: APP!$D$17
Name salario: APP!$D$16
Name sugestao_investimento: APP!$D$18
Name taxa_mensal: APP!$D$24

Sheet APP
B15: CONFIGURAÇÕES
B16: Salário | D16: 7000
B17: Rendimento Carteira | D17: 0.01
B18: Sugestão de Investimento (30%) | D18: =D16*30% -> 2100
B21: INVESTIMENTO MENSAL
B22: Quanto investir por mês | D22: 1500
B23: Por Quantos Anos | D23: 5
B24: Taxa de Rendimento Mensal | D24: 0.011
B25: Patrimônio acumulado | D25: =FV(taxa_mensal,qtd_anos*12,aporte*-1) -> 126522.64
B26: Dividendos Mensais | D26: =patrimonio*rendimento_carteira -> 1265.2264
B29: CENÁRIOS | D29: Dividendo
A30: 2 | B30: Quanto em 2 Anos | C30: =FV($D$24,$A30*12,$D$22*-1) -> 40943.538 | D30: =C30*rendimento_carteira -> 409.43538
A31: 5 | B31: Quanto em 5 Anos | C31: =FV($D$24,$A31*12,$D$22*-1) -> 126522.64 | D31: =C31*rendimento_carteira -> 1265.2264
A32: 10 | B32: Quanto em 10 Anos | C32: =FV($D$24,$A32*12,$D$22*-1) -> 370437.11 | D32: =C32*rendimento_carteira -> 3704.3711
A33: 20 | B33: Quanto em 20 Anos | C33: =FV($D$24,$A33*12,$D$22*-1) -> 1747181 | D33: =C33*rendimento_carteira -> 17471.81
A34: 30 | B34: Quanto em 30 Anos | C34: =FV($D$24,$A34*12,$D$22*-1) -> 6863903.1 | D34: =C34*rendimento_carteira -> 68639.031
B37: PERFIL | C37: Arrojado
B38: VALOR A SER INVESTIDO POR MÊS | C38: =aporte -> 1500
B40: TIPO DE FII | C40: Percentual Sugerido | D40: Valores
B41: DESENVOLVIMENTO | C41: =VLOOKUP($C$37&"-"&B41,'Base de Dados'!$A:$D,4,FALSE) -> 0.3 | D41: =C41*$C$38 -> 450
B42: RECEBÍVEIS | C42: =VLOOKUP($C$37&"-"&B42,'Base de Dados'!$A:$D,4,FALSE) -> 0.2 | D42: =C42*$C$38 -> 300
B43: GALPÕES | C43: =VLOOKUP($C$37&"-"&B43,'Base de Dados'!$A:$D,4,FALSE) -> 0.2 | D43: =C43*$C$38 -> 300
B44: PAPEL | C44: =VLOOKUP($C$37&"-"&B44,'Base de Dados'!$A:$D,4,FALSE) -> 0.15 | D44: =C44*$C$38 -> 225
B45: TIJOLO | C45: =VLOOKUP($C$37&"-"&B45,'Base de Dados'!$A:$D,4,FALSE) -> 0.15 | D45: =C45*$C$38 -> 225
D46: =SUM(D41:D45) -> 1500

Sheet Base de Dados
A2: CHAVE | B2: PERFIL | C2: TIPO DE FII | D2: %
A3: =$B$3&"-"&C3 -> Conservador-DESENVOLVIMENTO | B3: Conservador | C3: DESENVOLVIMENTO | D3: 0.05
A4: =$B$3&"-"&C4 -> Conservador-RECEBÍVEIS | B4: Conservador | C4: RECEBÍVEIS | D4: 0.05
A5: =$B$3&"-"&C5 -> Conservador-GALPÕES | B5: Conservador | C5: GALPÕES | D5: 0.1
A6: =$B$3&"-"&C6 -> Conservador-PAPEL | B6: Conservador | C6: PAPEL | D6: 0.3
A7: =$B$3&"-"&C7 -> Conservador-TIJOLO | B7: Conservador | C7: TIJOLO | D7: 0.5
A8: =$B$8&"-"&C8 -> Moderado-DESENVOLVIMENTO | B8: Moderado | C8: DESENVOLVIMENTO | D8: 0.1
A9: =$B$8&"-"&C9 -> Moderado-RECEBÍVEIS | B9: Moderado | C9: RECEBÍVEIS | D9: 0.1
A10: =$B$8&"-"&C10 -> Moderado-GALPÕES | B10: Moderado | C10: GALPÕES | D10: 0.2
A11: =$B$8&"-"&C11 -> Moderado-PAPEL | B11: Moderado | C11: PAPEL | D11: 0.3
A12: =$B$8&"-"&C12 -> Moderado-TIJOLO | B12: Moderado | C12: TIJOLO | D12: 0.3
A13: =$B$13&"-"&C13 -> Arrojado-DESENVOLVIMENTO | B13: Arrojado | C13: DESENVOLVIMENTO | D13: 0.3
A14: =$B$13&"-"&C14 -> Arrojado-RECEBÍVEIS | B14: Arrojado | C14: RECEBÍVEIS | D14: 0.2
A15: =$B$13&"-"&C15 -> Arrojado-GALPÕES | B15: Arrojado | C15: GALPÕES | D15: 0.2
A16: =$B$13&"-"&C16 -> Arrojado-PAPEL | B16: Arrojado | C16: PAPEL | D16: 0.15
A17: =$B$13&"-"&C17 -> Arrojado-TIJOLO | B17: Arrojado | C17: TIJOLO | D17: 0.15
